Metadata-Version: 1.1
Name: scalr-api
Version: 1.0.1
Summary: Scalr REST API Python Wrapper
Home-page: https://github.com/Nrupesh29/scalr-api
Author: Nrupesh Patel
Author-email: nrupesh.patel2912@gmail.com
License: MIT
Download-URL: https://github.com/Nrupesh29/scalr-api
Keywords: scalr infrastructure software rest api
Platform: UNKNOWN
Classifier: Development Status :: 4 - Beta
Classifier: Intended Audience :: Developers
Classifier: License :: OSI Approved :: MIT License
Classifier: Topic :: Software Development :: Libraries :: Python Modules
